pyobs_tui/__init__.py
pyobs_tui/app.py
pyobs_tui/tui.py
pyobs_tui-0.0.1.dist-info/WHEEL
pyobs_tui-0.0.1.dist-info/METADATA
pyobs_tui-0.0.1.dist-info/RECORD
