Metadata-Version: 2.4
Name: pyobs-tui
Version: 0.0.1
Summary: A remote TUI for pyobs
Author: Tim-Oliver Husser
Author-email: Tim-Oliver Husser <thusser@uni-goettingen.de>
License-Expression: MIT
Requires-Dist: pyobs-core>=1.34.0
Requires-Dist: textual>=6.7.1
Requires-Python: >=3.11, <=3.14
